airtable_mcp/__init__.py
airtable_mcp/__main__.py
airtable_mcp/server.py
airtable_mcp-0.1.3.dist-info/METADATA
airtable_mcp-0.1.3.dist-info/WHEEL
airtable_mcp-0.1.3.dist-info/entry_points.txt
airtable_mcp-0.1.3.dist-info/licenses/LICENSE
airtable_mcp-0.1.3.dist-info/RECORD
