Metadata-Version: 2.4
Name: airtable-mcp
Version: 0.1.3
Summary: A local MCP server for interacting with Airtable via Claude.
Author-email: Alex Brufsky <alex@brufsky.org>
License: MIT
License-File: LICENSE
Requires-Python: >=3.10
Requires-Dist: airtable-python-wrapper>=0.15.3
Requires-Dist: anthropic>=0.19.1
Requires-Dist: mcp>=1.6.0
Requires-Dist: pydantic>=2.4.2
Requires-Dist: python-dotenv>=1.0.0
Requires-Dist: requests>=2.31.0
Requires-Dist: typing-extensions>=4.7.1
Requires-Dist: websockets>=11.0.3
